04-VLSI_4/Mux4_1_Assgn/Mux4_1_Assgn.v
module Mux4_1_Assgn(i0, i1, i2, i3, s0, s1, out);
    input i0, i1, i2, i3, s0, s1;
    output out;
    assign out = (~s1 & ~s0 & i0) | 
                 (~s1 & s0 & i1) | 
                 (s1 & ~s0 & i2) | 
                 (s1 & s0 & i3);
endmodule

04-VLSI_4/Mux4_1_Assgn/tb_Mux4_1_Assgn.v
module tb_Mux4_1_Assgn;
    reg i0, i1, i2, i3, s0, s1;
    wire out;

    Mux4_1_Assgn uut (.i0(i0), .i1(i1), .i2(i2), .i3(i3), .s0(s0), .s1(s1), .out(out));

    initial begin
        $dumpfile("tb_Mux4_1_Assgn.vcd");
        $dumpvars(0, tb_Mux4_1_Assgn);

        i0 = 0; i1 = 0; i2 = 0; i3 = 0; s0 = 0; s1 = 0; #10;
        i0 = 1; i1 = 0; i2 = 0; i3 = 0; s0 = 0; s1 = 0; #10;
        i0 = 1; i1 = 0; i2 = 0; i3 = 0; s0 = 1; s1 = 0; #10;
        i0 = 1; i1 = 1; i2 = 0; i3 = 0; s0 = 1; s1 = 0; #10;
        i0 = 1; i1 = 1; i2 = 0; i3 = 0; s0 = 0; s1 = 1; #10;
        i0 = 1; i1 = 1; i2 = 1; i3 = 0; s0 = 0; s1 = 1; #10;
        i0 = 1; i1 = 1; i2 = 1; i3 = 0; s0 = 1; s1 = 1; #10;
        i0 = 1; i1 = 1; i2 = 1; i3 = 1; s0 = 1; s1 = 1; #10;

        $finish;
    end
endmodule

04-VLSI_4/Mux4_1_Assgn/tb_Mux4_1_Assgn.vcd
$date
	Wed Jun 18 14:50:57 2025
$end
$version
	ModelSim Version 2020.1
$end
$timescale
	1ps
$end

$scope module tb_Mux4_1_Assgn $end
$var reg 1 ! i0 $end
$var reg 1 " i1 $end
$var reg 1 # i2 $end
$var reg 1 $ i3 $end
$var reg 1 % s0 $end
$var reg 1 & s1 $end
$var wire 1 ' out $end

$scope module uut $end
$var wire 1 ( i0 $end
$var wire 1 ) i1 $end
$var wire 1 * i2 $end
$var wire 1 + i3 $end
$var wire 1 , s0 $end
$var wire 1 - s1 $end
$var wire 1 ' out $end
$upscope $end
$upscope $end
$enddefinitions $end
#0
$dumpvars
0!
0"
0#
0$
0%
0&
0'
0-
0,
0+
0*
0)
0(
$end
#10
1!
1(
1'
#20
1%
1,
0'
#30
1"
1)
1'
#40
0%
1&
0,
1-
0'
#50
1#
1*
1'
#60
1%
1,
0'
#70
1$
1+
1'
