04-VLSI_4/Mux4_1_Alwys/Mux4_1_Alwys.v
module Mux4_1_Alwys(i0, i1, i2, i3, s0, s1, out);
    input i0, i1, i2, i3, s0, s1;
    output reg out;
    always @(i0, i1, i2, i3, s0, s1) begin
        case ({s1, s0})
            2'b00: out = i0;
            2'b01: out = i1;
            2'b10: out = i2;
            2'b11: out = i3;
            default: out = 1'b0;
        endcase
    end
endmodule

04-VLSI_4/Mux4_1_Alwys/tb_Mux4_1_Alwys.v
module tb_Mux4_1_Alwys;
    reg i0, i1, i2, i3, s0, s1;
    wire out;
    Mux4_1_Alwys uut (.i0(i0), .i1(i1), .i2(i2), .i3(i3), .s0(s0), .s1(s1), .out(out));
    initial begin
        $dumpfile("tb_Mux4_1_Alwys.vcd");
        $dumpvars(0, tb_Mux4_1_Alwys);
        i0 = 0; i1 = 0; i2 = 0; i3 = 0; s0 = 0; s1 = 0;
        #10;
        i0 = 1; i1 = 0; i2 = 0; i3 = 0; s0 = 0; s1 = 0;
        #10;
        i0 = 1; i1 = 0; i2 = 0; i3 = 0; s0 = 1; s1 = 0;
        #10;
        i0 = 1; i1 = 1; i2 = 0; i3 = 0; s0 = 1; s1 = 0;
        #10;
        i0 = 1; i1 = 1; i2 = 0; i3 = 0; s0 = 0; s1 = 1;
        #10;
        i0 = 1; i1 = 1; i2 = 1; i3 = 0; s0 = 0; s1 = 1;
        #10;
        i0 = 1; i1 = 1; i2 = 1; i3 = 0; s0 = 1; s1 = 1;
        #10;
        i0 = 1; i1 = 1; i2 = 1; i3 = 1; s0 = 1; s1 = 1;
        #10;
        $finish;
    end
endmodule

04-VLSI_4/Mux4_1_Alwys/tb_Mux4_1_Alwys.vcd
$date
	Wed Jun 18 14:58:49 2025
$end
$version
	ModelSim Version 2020.1
$end
$timescale
	1ps
$end

$scope module tb_Mux4_1_Alwys $end
$var reg 1 ! i0 $end
$var reg 1 " i1 $end
$var reg 1 # i2 $end
$var reg 1 $ i3 $end
$var reg 1 % s0 $end
$var reg 1 & s1 $end
$var wire 1 ' out $end

$scope module uut $end
$var wire 1 ( i0 $end
$var wire 1 ) i1 $end
$var wire 1 * i2 $end
$var wire 1 + i3 $end
$var wire 1 , s0 $end
$var wire 1 - s1 $end
$var reg 1 . out $end
$upscope $end
$upscope $end
$enddefinitions $end
#0
$dumpvars
0!
0"
0#
0$
0%
0&
0.
0'
0-
0,
0+
0*
0)
0(
$end
#10
1!
1(
1.
1'
#20
1%
1,
0.
0'
#30
1"
1)
1.
1'
#40
0%
1&
0,
1-
0.
0'
#50
1#
1*
1.
1'
#60
1%
1,
0.
0'
#70
1$
1+
1.
1'
